seasave_data_post_processing/__init__.py
seasave_data_post_processing/data_post_processing.py
seasave_data_post_processing/path_xml.py
seasave_data_post_processing-0.0.1.dist-info/LICENSE
seasave_data_post_processing-0.0.1.dist-info/WHEEL
seasave_data_post_processing-0.0.1.dist-info/METADATA
seasave_data_post_processing-0.0.1.dist-info/RECORD
